odoo/addons/fleet_vehicle_usage/README.rst
odoo/addons/fleet_vehicle_usage/__init__.py
odoo/addons/fleet_vehicle_usage/__manifest__.py
odoo/addons/fleet_vehicle_usage/data/ir_sequence_data.xml
odoo/addons/fleet_vehicle_usage/i18n/es.po
odoo/addons/fleet_vehicle_usage/i18n/fleet_vehicle_usage.pot
odoo/addons/fleet_vehicle_usage/i18n/it.po
odoo/addons/fleet_vehicle_usage/models/__init__.py
odoo/addons/fleet_vehicle_usage/models/fleet_vehicle.py
odoo/addons/fleet_vehicle_usage/models/fleet_vehicle_usage.py
odoo/addons/fleet_vehicle_usage/readme/CONTRIBUTORS.md
odoo/addons/fleet_vehicle_usage/readme/DESCRIPTION.md
odoo/addons/fleet_vehicle_usage/security/ir.model.access.csv
odoo/addons/fleet_vehicle_usage/security/security.xml
odoo/addons/fleet_vehicle_usage/static/description/icon.png
odoo/addons/fleet_vehicle_usage/static/description/index.html
odoo/addons/fleet_vehicle_usage/tests/__init__.py
odoo/addons/fleet_vehicle_usage/tests/test_fleet_vehicle_usage.py
odoo/addons/fleet_vehicle_usage/views/fleet_vehicle_usage_view.xml
odoo/addons/fleet_vehicle_usage/views/fleet_vehicle_view.xml
odoo_addon_fleet_vehicle_usage-17.0.1.0.0.6.dist-info/METADATA
odoo_addon_fleet_vehicle_usage-17.0.1.0.0.6.dist-info/WHEEL
odoo_addon_fleet_vehicle_usage-17.0.1.0.0.6.dist-info/top_level.txt
odoo_addon_fleet_vehicle_usage-17.0.1.0.0.6.dist-info/RECORD
