Metadata-Version: 2.1
Name: odoo-addon-fleet_vehicle_usage
Version: 17.0.1.0.0.6
Requires-Python: >=3.10
Requires-Dist: odoo>=17.0a,<17.1dev
Summary: Fleet Vehicle Usage
Home-page: https://github.com/OCA/fleet
License: AGPL-3
Author: =?utf-8?q?C=C3=A9sar_Fern=C3=A1ndez=2C_Tecnativa=2C_Odoo_Community_Association_=28OCA=29?=
Author-email: support@odoo-community.org
Classifier: Programming Language :: Python
Classifier: Framework :: Odoo
Classifier: Framework :: Odoo :: 17.0
Classifier: License :: OSI Approved :: GNU Affero General Public License v3
